{
 "totals": {
  "totalLoaves": 0,
  "totalMuffins": 0,
  "totalBagels": 0,
  "totalFocaccia": 2,
  "totalSimple": null,
  "totalEnriched": null,
  "batches": 1,
  "mixBatches": 1,
  "bagelBatches": null
 },
 "events": [
  {
   "t": "2026-01-17T10:37:00.000Z",
   "tEnd": null,
   "title": "Gather ingredients",
   "detail": "5 min active",
   "process": "focaccia",
   "columnKey": "focaccia",
   "colDetails": null,
   "stage": null,
   "stageType": null,
   "equip": null,
   "equipStrip": null,
   "equipStripTitle": null,
   "container": null,
   "activeStep": null,
   "activeMin": 5,
   "mixBatchCount": null,
   "mixBatchContents": null,
   "batchIngredients": null
  },
  {
   "t": "2026-01-17T10:42:00.000Z",
   "tEnd": null,
   "title": "Mix focaccia dough",
   "detail": "10 min mix · then 20 min rest · commercial yeast, no levain needed",
   "process": "focaccia",
   "columnKey": "focaccia",
   "colDetails": null,
   "stage": null,
   "stageType": null,
   "equip": null,
   "equipStrip": null,
   "equipStripTitle": null,
   "container": null,
   "activeStep": null,
   "activeMin": 10,
   "mixBatchCount": null,
   "mixBatchContents": null,
   "batchIngredients": null
  },
  {
   "t": "2026-01-17T11:12:00.000Z",
   "tEnd": null,
   "title": "Stretch & fold 1 of 4 — focaccia",
   "detail": "5 min active · next fold in 15 min",
   "process": "focaccia",
   "columnKey": "focaccia",
   "colDetails": null,
   "stage": null,
   "stageType": null,
   "equip": null,
   "equipStrip": null,
   "equipStripTitle": null,
   "container": null,
   "activeStep": null,
   "activeMin": 5,
   "mixBatchCount": null,
   "mixBatchContents": null,
   "batchIngredients": null
  },
  {
   "t": "2026-01-17T11:27:00.000Z",
   "tEnd": null,
   "title": "Stretch & fold 2 of 4 — focaccia",
   "detail": "5 min active · next fold in 15 min",
   "process": "focaccia",
   "columnKey": "focaccia",
   "colDetails": null,
   "stage": null,
   "stageType": null,
   "equip": null,
   "equipStrip": null,
   "equipStripTitle": null,
   "container": null,
   "activeStep": null,
   "activeMin": 5,
   "mixBatchCount": null,
   "mixBatchContents": null,
   "batchIngredients": null
  },
  {
   "t": "2026-01-17T11:42:00.000Z",
   "tEnd": null,
   "title": "Stretch & fold 3 of 4 — focaccia",
   "detail": "5 min active · next fold in 15 min",
   "process": "focaccia",
   "columnKey": "focaccia",
   "colDetails": null,
   "stage": null,
   "stageType": null,
   "equip": null,
   "equipStrip": null,
   "equipStripTitle": null,
   "container": null,
   "activeStep": null,
   "activeMin": 5,
   "mixBatchCount": null,
   "mixBatchContents": null,
   "batchIngredients": null
  },
  {
   "t": "2026-01-17T11:57:00.000Z",
   "tEnd": null,
   "title": "Stretch & fold 4 of 4 (last) — focaccia",
   "detail": "5 min active · then 75 min bulk ferment",
   "process": "focaccia",
   "columnKey": "focaccia",
   "colDetails": null,
   "stage": null,
   "stageType": null,
   "equip": null,
   "equipStrip": null,
   "equipStripTitle": null,
   "container": null,
   "activeStep": null,
   "activeMin": 5,
   "mixBatchCount": null,
   "mixBatchContents": null,
   "batchIngredients": null
  },
  {
   "t": "2026-01-17T12:47:00.000Z",
   "tEnd": null,
   "title": "Turn on oven to 475°F",
   "detail": "~90 min preheat",
   "process": "focaccia",
   "columnKey": "focaccia",
   "colDetails": null,
   "stage": "bake",
   "stageType": null,
   "equip": null,
   "equipStrip": null,
   "equipStripTitle": null,
   "container": null,
   "activeStep": null,
   "activeMin": 0,
   "mixBatchCount": null,
   "mixBatchContents": null,
   "batchIngredients": null
  },
  {
   "t": "2026-01-17T13:12:00.000Z",
   "tEnd": null,
   "title": "Shape focaccia — transfer to pans",
   "detail": "10 min × 2 pans = 20 min · oil pan, stretch dough to fit, dimple · 705 g per pan",
   "process": "focaccia",
   "columnKey": "focaccia",
   "colDetails": null,
   "stage": null,
   "stageType": null,
   "equip": null,
   "equipStrip": null,
   "equipStripTitle": null,
   "container": null,
   "activeStep": null,
   "activeMin": 10,
   "mixBatchCount": null,
   "mixBatchContents": null,
   "batchIngredients": null
  },
  {
   "t": "2026-01-17T13:32:00.000Z",
   "tEnd": null,
   "title": "Pan rise",
   "detail": "45 min room-temp pan rise",
   "process": "focaccia",
   "columnKey": "focaccia",
   "colDetails": null,
   "stage": null,
   "stageType": null,
   "equip": null,
   "equipStrip": null,
   "equipStripTitle": null,
   "container": null,
   "activeStep": null,
   "activeMin": 0,
   "mixBatchCount": null,
   "mixBatchContents": null,
   "batchIngredients": null
  },
  {
   "t": "2026-01-17T14:17:00.000Z",
   "tEnd": "2026-01-17T14:40:00.000Z",
   "title": "Bake focaccia",
   "detail": "2 pans · 23 min · 475°F",
   "process": "focaccia",
   "columnKey": "focaccia",
   "colDetails": null,
   "stage": null,
   "stageType": null,
   "equip": [],
   "equipStrip": "",
   "equipStripTitle": null,
   "container": null,
   "activeStep": null,
   "activeMin": 0,
   "mixBatchCount": null,
   "mixBatchContents": null,
   "batchIngredients": null
  },
  {
   "t": "2026-01-17T14:40:00.000Z",
   "tEnd": null,
   "title": "Last focaccia out — start cooling",
   "detail": "20 min cool",
   "process": "focaccia",
   "columnKey": "focaccia",
   "colDetails": null,
   "stage": null,
   "stageType": null,
   "equip": null,
   "equipStrip": null,
   "equipStripTitle": null,
   "container": null,
   "activeStep": null,
   "activeMin": 0,
   "mixBatchCount": null,
   "mixBatchContents": null,
   "batchIngredients": null
  },
  {
   "t": "2026-01-17T15:00:00.000Z",
   "tEnd": null,
   "title": "Package & ready for sale",
   "detail": "",
   "process": "focaccia",
   "columnKey": "focaccia",
   "colDetails": null,
   "stage": null,
   "stageType": null,
   "equip": null,
   "equipStrip": null,
   "equipStripTitle": null,
   "container": null,
   "activeStep": null,
   "activeMin": 0,
   "mixBatchCount": null,
   "mixBatchContents": null,
   "batchIngredients": null
  }
 ],
 "warnings": [
  {
   "msg": "2 active focaccia steps fall outside kitchen hours (6 AM–10 PM) (Gather ingredients, Mix focaccia dough). Try a different bake time.",
   "issue": "late-night",
   "kind": "focaccia",
   "type": null
  },
  {
   "msg": "Fermentation and levain timing assume a 70°F proofing temperature (default). Set your kitchen's proofing temp in the Kitchen tab for more accurate timing.",
   "issue": "proofing-temp-default",
   "kind": null,
   "type": "info"
  }
 ],
 "equipClaims": [
  {
   "pool": "oven",
   "role": "Focaccia bake",
   "name": "Oven",
   "count": 1,
   "start": "2026-01-17T14:17:00.000Z",
   "end": "2026-01-17T14:40:00.000Z",
   "capacity": 1
  }
 ],
 "columns": {
  "loaf": null,
  "muffin": null,
  "bagel": null,
  "focaccia": null,
  "side": null
 },
 "levain": {
  "build1Opt": null,
  "build2Opt": null,
  "useSeparateLevains": null,
  "muffinBuild1Opt": null,
  "muffinBuild2Opt": null,
  "bagelBuild1Opt": null,
  "bagelBuild2Opt": null,
  "useBagelSeparateLevain": null,
  "levainContainerInfo": null
 },
 "loafContainerInfo": null,
 "loafColdProofRange": null
}
